{
  "formula": "log_he_she_odds ~ C(tense) + C(semantic_role) + C(syntactic_role) + C(valence) + C(dominance) + log_frequency + lex_emb_norm + C(tense):C(semantic_role) + C(tense):C(valence) + C(tense):log_frequency + C(tense):lex_emb_norm + C(semantic_role):C(syntactic_role) + C(semantic_role):C(valence) + C(semantic_role):C(dominance) + C(semantic_role):lex_emb_norm + C(syntactic_role):C(valence) + C(syntactic_role):C(dominance) + C(syntactic_role):log_frequency + C(syntactic_role):lex_emb_norm + C(valence):C(dominance) + C(valence):lex_emb_norm + C(dominance):log_frequency + C(dominance):lex_emb_norm + log_frequency:lex_emb_norm + profession_embedding_1 + profession_embedding_2 + profession_embedding_3 + profession_embedding_4 + profession_embedding_5",
  "model_type": "OLS",
  "optimizer": "closed_form",
  "converged": true,
  "nobs": 15360,
  "aic": 48537.32005761752,
  "bic": 48919.2961579526,
  "log_likelihood": -24218.66002880876,
  "residual_variance": 1.3755515934635376,
  "R2m": 0.3221466683067742,
  "R2c": 0.3221466683067742,
  "warnings": [],
  "fixed_effect_variance_profession_embedding": 1.0823989017241358,
  "fixed_effect_variance_Intercept": 0.0,
  "fixed_effect_variance_C(tense)": 0.034868807000274976,
  "fixed_effect_variance_C(semantic_role)": 0.0017358598081866127,
  "fixed_effect_variance_C(syntactic_role)": 0.04938402860797026,
  "fixed_effect_variance_C(valence)": 0.01346783504218413,
  "fixed_effect_variance_C(dominance)": 0.025496421608963878,
  "fixed_effect_variance_C(tense):C(semantic_role)": 0.0016022053176254583,
  "fixed_effect_variance_C(tense):C(valence)": 0.000894625673095805,
  "fixed_effect_variance_C(semantic_role):C(syntactic_role)": 0.0022697622637181942,
  "fixed_effect_variance_C(semantic_role):C(valence)": 0.0002646340865301526,
  "fixed_effect_variance_C(semantic_role):C(dominance)": 0.0002799994392207232,
  "fixed_effect_variance_C(syntactic_role):C(valence)": 0.0001981118469468594,
  "fixed_effect_variance_C(syntactic_role):C(dominance)": 0.001211620784349716,
  "fixed_effect_variance_C(valence):C(dominance)": 0.0004667322286397842,
  "fixed_effect_variance_log_frequency": 44.40066309677708,
  "fixed_effect_variance_C(tense):log_frequency": 0.029954804494885093,
  "fixed_effect_variance_C(syntactic_role):log_frequency": 0.0033819838182946337,
  "fixed_effect_variance_C(dominance):log_frequency": 0.0024754891626204588,
  "fixed_effect_variance_lex_emb_norm": 3.597591280062436,
  "fixed_effect_variance_C(tense):lex_emb_norm": 0.06758566711454905,
  "fixed_effect_variance_C(semantic_role):lex_emb_norm": 0.008861402577819701,
  "fixed_effect_variance_C(syntactic_role):lex_emb_norm": 0.04366181239433357,
  "fixed_effect_variance_C(valence):lex_emb_norm": 0.005556791934819368,
  "fixed_effect_variance_C(dominance):lex_emb_norm": 0.04488526347971816,
  "fixed_effect_variance_log_frequency:lex_emb_norm": 76.37472357568565
}