{
  "formula": "log_he_she_odds ~ C(tense) + C(semantic_role) + C(syntactic_role) + C(valence) + C(dominance) + log_frequency + lex_emb_norm + C(tense):C(syntactic_role) + C(tense):C(valence) + C(tense):C(dominance) + C(semantic_role):C(syntactic_role) + C(semantic_role):C(valence) + C(semantic_role):C(dominance) + C(semantic_role):log_frequency + C(semantic_role):lex_emb_norm + C(syntactic_role):C(valence) + C(syntactic_role):C(dominance) + C(syntactic_role):log_frequency + C(syntactic_role):lex_emb_norm + C(valence):C(dominance) + C(valence):lex_emb_norm + log_frequency:lex_emb_norm + profession_embedding_1 + profession_embedding_2 + profession_embedding_3 + profession_embedding_4 + profession_embedding_5",
  "model_type": "OLS",
  "optimizer": "closed_form",
  "converged": true,
  "nobs": 15360,
  "aic": 54148.66908767958,
  "bic": 54484.80805597445,
  "log_likelihood": -27030.33454383979,
  "residual_variance": 1.982911934056735,
  "R2m": 0.28187559522306294,
  "R2c": 0.28187559522306294,
  "warnings": [],
  "fixed_effect_variance_profession_embedding": 1.3813843923242737,
  "fixed_effect_variance_Intercept": 5.049038506858933e-29,
  "fixed_effect_variance_C(tense)": 0.044882033732226274,
  "fixed_effect_variance_C(semantic_role)": 0.0027662047140515327,
  "fixed_effect_variance_C(syntactic_role)": 0.12094941371087083,
  "fixed_effect_variance_C(valence)": 0.0012551582112786846,
  "fixed_effect_variance_C(dominance)": 0.001902783758204617,
  "fixed_effect_variance_C(tense):C(syntactic_role)": 0.0033271493946557076,
  "fixed_effect_variance_C(tense):C(valence)": 0.0051744923743126505,
  "fixed_effect_variance_C(tense):C(dominance)": 0.007703377280711932,
  "fixed_effect_variance_C(semantic_role):C(syntactic_role)": 0.006239473700490942,
  "fixed_effect_variance_C(semantic_role):C(valence)": 0.0006217927693442829,
  "fixed_effect_variance_C(semantic_role):C(dominance)": 0.00013872383837222586,
  "fixed_effect_variance_C(syntactic_role):C(valence)": 0.0020814205491543783,
  "fixed_effect_variance_C(syntactic_role):C(dominance)": 0.0023882115171912836,
  "fixed_effect_variance_C(valence):C(dominance)": 0.00024275491479295268,
  "fixed_effect_variance_log_frequency": 0.1816775866943568,
  "fixed_effect_variance_C(semantic_role):log_frequency": 0.001016449206298069,
  "fixed_effect_variance_C(syntactic_role):log_frequency": 0.0061854682480017315,
  "fixed_effect_variance_lex_emb_norm": 0.6498033959112212,
  "fixed_effect_variance_C(semantic_role):lex_emb_norm": 0.0025415329478613727,
  "fixed_effect_variance_C(syntactic_role):lex_emb_norm": 0.000461106732987228,
  "fixed_effect_variance_C(valence):lex_emb_norm": 0.0002392313167430409,
  "fixed_effect_variance_log_frequency:lex_emb_norm": 3.3635417070815334
}