{
  "formula": "log_he_she_odds ~ C(tense) + C(semantic_role) + C(syntactic_role) + C(valence) + C(dominance) + log_frequency + lex_emb_norm + C(tense):C(syntactic_role) + C(tense):C(valence) + C(tense):C(dominance) + C(tense):log_frequency + C(semantic_role):C(syntactic_role) + C(semantic_role):C(valence) + C(semantic_role):log_frequency + C(syntactic_role):C(valence) + C(syntactic_role):C(dominance) + C(syntactic_role):log_frequency + C(valence):log_frequency + log_frequency:lex_emb_norm + profession_embedding_1 + profession_embedding_2 + profession_embedding_3 + profession_embedding_4 + profession_embedding_5",
  "model_type": "OLS",
  "optimizer": "closed_form",
  "converged": true,
  "nobs": 15360,
  "aic": 51840.69307967546,
  "bic": 52184.47156997704,
  "log_likelihood": -25875.34653983773,
  "residual_variance": 1.7061556272761045,
  "R2m": 0.25708464815608345,
  "R2c": 0.25708464815608345,
  "warnings": [],
  "fixed_effect_variance_profession_embedding": 1.247487380308455,
  "fixed_effect_variance_Intercept": 1.2622596267147332e-29,
  "fixed_effect_variance_C(tense)": 0.011385774656551747,
  "fixed_effect_variance_C(semantic_role)": 0.008909902672290226,
  "fixed_effect_variance_C(syntactic_role)": 0.05174184588795037,
  "fixed_effect_variance_C(valence)": 0.017316127399647812,
  "fixed_effect_variance_C(dominance)": 0.002581273729012916,
  "fixed_effect_variance_C(tense):C(syntactic_role)": 0.003696621340817187,
  "fixed_effect_variance_C(tense):C(valence)": 0.0026266742319492244,
  "fixed_effect_variance_C(tense):C(dominance)": 0.0013241877986582393,
  "fixed_effect_variance_C(semantic_role):C(syntactic_role)": 0.0017530198802927445,
  "fixed_effect_variance_C(semantic_role):C(valence)": 0.0023135704579159487,
  "fixed_effect_variance_C(syntactic_role):C(valence)": 0.003684345841818882,
  "fixed_effect_variance_C(syntactic_role):C(dominance)": 0.0013568469589717229,
  "fixed_effect_variance_log_frequency": 7.739625674637293,
  "fixed_effect_variance_C(tense):log_frequency": 0.010177305030815027,
  "fixed_effect_variance_C(semantic_role):log_frequency": 0.0026926379300834026,
  "fixed_effect_variance_C(syntactic_role):log_frequency": 0.016636817290101573,
  "fixed_effect_variance_C(valence):log_frequency": 0.0010561272562271981,
  "fixed_effect_variance_lex_emb_norm": 2.683184230784553,
  "fixed_effect_variance_log_frequency:lex_emb_norm": 11.635238598515695
}