{
  "formula": "log_he_she_odds ~ C(tense) + C(semantic_role) + C(syntactic_role) + C(valence) + C(dominance) + log_frequency + lex_emb_norm + C(tense):C(semantic_role) + C(tense):C(syntactic_role) + C(tense):C(valence) + C(tense):C(dominance) + C(tense):log_frequency + C(tense):lex_emb_norm + C(semantic_role):C(syntactic_role) + C(semantic_role):C(valence) + C(semantic_role):C(dominance) + C(semantic_role):log_frequency + C(semantic_role):lex_emb_norm + C(syntactic_role):C(valence) + C(syntactic_role):C(dominance) + C(syntactic_role):log_frequency + C(syntactic_role):lex_emb_norm + C(valence):C(dominance) + C(valence):lex_emb_norm + C(dominance):log_frequency + C(dominance):lex_emb_norm + log_frequency:lex_emb_norm",
  "re_formula": "1 + C(semantic_role) + C(syntactic_role) + C(valence) + C(dominance)",
  "group_col": "profession",
  "optimizer": "lbfgs",
  "converged": true,
  "warning_count": 1,
  "warnings": [
    "ConvergenceWarning: The MLE may be on the boundary of the parameter space."
  ],
  "numerical_issue_warnings": true,
  "aic": 15676.957769060507,
  "bic": 16227.003353543027,
  "log_likelihood": -7766.478884530254,
  "nobs": 15360,
  "residual_variance": 0.15571399612701836,
  "R2m": 0.024701367828672327,
  "R2c": 0.9351251743716913,
  "fixed_effect_variance_Intercept": 7.889122666967083e-31,
  "fixed_effect_variance_C(tense)": 0.005215350052120355,
  "fixed_effect_variance_C(semantic_role)": 0.013655070166216437,
  "fixed_effect_variance_C(syntactic_role)": 0.01348083153126227,
  "fixed_effect_variance_C(valence)": 0.011353226108287593,
  "fixed_effect_variance_C(dominance)": 0.0002623939197619219,
  "fixed_effect_variance_C(tense):C(semantic_role)": 0.0026823904559104147,
  "fixed_effect_variance_C(tense):C(syntactic_role)": 0.0031667293784402965,
  "fixed_effect_variance_C(tense):C(valence)": 0.0013111969943544162,
  "fixed_effect_variance_C(tense):C(dominance)": 0.0017316542799524915,
  "fixed_effect_variance_C(semantic_role):C(syntactic_role)": 0.008519498917510634,
  "fixed_effect_variance_C(semantic_role):C(valence)": 2.8951998985857088e-05,
  "fixed_effect_variance_C(semantic_role):C(dominance)": 5.17003854302725e-07,
  "fixed_effect_variance_C(syntactic_role):C(valence)": 0.0028316961586346565,
  "fixed_effect_variance_C(syntactic_role):C(dominance)": 0.0005443245804708835,
  "fixed_effect_variance_C(valence):C(dominance)": 8.68299601626512e-05,
  "fixed_effect_variance_log_frequency": 0.09467052130994479,
  "fixed_effect_variance_C(tense):log_frequency": 0.006571129501857871,
  "fixed_effect_variance_C(semantic_role):log_frequency": 0.0029695557560176756,
  "fixed_effect_variance_C(syntactic_role):log_frequency": 0.01007515184679033,
  "fixed_effect_variance_C(dominance):log_frequency": 0.00015573413242761256,
  "fixed_effect_variance_lex_emb_norm": 0.029370238841620964,
  "fixed_effect_variance_C(tense):lex_emb_norm": 0.0009345952795139609,
  "fixed_effect_variance_C(semantic_role):lex_emb_norm": 0.001116373058424341,
  "fixed_effect_variance_C(syntactic_role):lex_emb_norm": 0.0030894607158289864,
  "fixed_effect_variance_C(valence):lex_emb_norm": 7.208145256404824e-05,
  "fixed_effect_variance_C(dominance):lex_emb_norm": 1.423018857551644e-05,
  "fixed_effect_variance_log_frequency:lex_emb_norm": 0.10572456565520018,
  "random_effect_variance_semantic_role": 0.0033660141136696155,
  "random_effect_variance_syntactic_role": 0.03344412826625511,
  "random_effect_variance_valence": 0.010209031072900285,
  "random_effect_variance_dominance": 0.006376890060869781
}