{
  "formula": "log_he_she_odds ~ C(tense) + C(semantic_role) + C(syntactic_role) + C(valence) + C(dominance) + log_frequency + lex_emb_norm + C(tense):C(semantic_role) + C(tense):C(syntactic_role) + C(tense):C(valence) + C(tense):C(dominance) + C(tense):lex_emb_norm + C(semantic_role):C(syntactic_role) + C(semantic_role):C(valence) + C(semantic_role):C(dominance) + C(semantic_role):log_frequency + C(semantic_role):lex_emb_norm + C(syntactic_role):C(valence) + C(syntactic_role):C(dominance) + C(syntactic_role):log_frequency + C(syntactic_role):lex_emb_norm + C(valence):C(dominance) + C(valence):log_frequency + C(valence):lex_emb_norm + C(dominance):log_frequency + C(dominance):lex_emb_norm + log_frequency:lex_emb_norm",
  "re_formula": "1 + C(semantic_role) + C(syntactic_role) + C(valence) + C(dominance)",
  "group_col": "profession",
  "optimizer": "lbfgs",
  "converged": true,
  "warning_count": 1,
  "warnings": [
    "ConvergenceWarning: The MLE may be on the boundary of the parameter space."
  ],
  "numerical_issue_warnings": true,
  "aic": 15707.406698066276,
  "bic": 16226.894194521989,
  "log_likelihood": -7785.703349033138,
  "nobs": 15360,
  "residual_variance": 0.15611152748480364,
  "R2m": 0.01842586715891319,
  "R2c": 0.9342303968685663,
  "fixed_effect_variance_Intercept": 0.0,
  "fixed_effect_variance_C(tense)": 0.005397198401690336,
  "fixed_effect_variance_C(semantic_role)": 0.012993887747902076,
  "fixed_effect_variance_C(syntactic_role)": 0.014412071722799364,
  "fixed_effect_variance_C(valence)": 0.009402920100281938,
  "fixed_effect_variance_C(dominance)": 0.00023523878177388394,
  "fixed_effect_variance_C(tense):C(semantic_role)": 0.00268239045591046,
  "fixed_effect_variance_C(tense):C(syntactic_role)": 0.003166729378440314,
  "fixed_effect_variance_C(tense):C(valence)": 0.001311196994354433,
  "fixed_effect_variance_C(tense):C(dominance)": 0.0017316542799525093,
  "fixed_effect_variance_C(semantic_role):C(syntactic_role)": 0.008519498917510608,
  "fixed_effect_variance_C(semantic_role):C(valence)": 2.895199898586139e-05,
  "fixed_effect_variance_C(semantic_role):C(dominance)": 5.17003854302184e-07,
  "fixed_effect_variance_C(syntactic_role):C(valence)": 0.002831696158634632,
  "fixed_effect_variance_C(syntactic_role):C(dominance)": 0.0005443245804708889,
  "fixed_effect_variance_C(valence):C(dominance)": 8.68299601626508e-05,
  "fixed_effect_variance_log_frequency": 0.027952459426492108,
  "fixed_effect_variance_C(semantic_role):log_frequency": 0.0023697426549180232,
  "fixed_effect_variance_C(syntactic_role):log_frequency": 0.011746023450000729,
  "fixed_effect_variance_C(valence):log_frequency": 0.0003783430997803673,
  "fixed_effect_variance_C(dominance):log_frequency": 0.00020241177822883958,
  "fixed_effect_variance_lex_emb_norm": 0.05664910746859728,
  "fixed_effect_variance_C(tense):lex_emb_norm": 0.0035045759736075212,
  "fixed_effect_variance_C(semantic_role):lex_emb_norm": 0.0009441309656537099,
  "fixed_effect_variance_C(syntactic_role):lex_emb_norm": 0.0026921226131904714,
  "fixed_effect_variance_C(valence):lex_emb_norm": 0.0003053751561887156,
  "fixed_effect_variance_C(dominance):lex_emb_norm": 2.0973137014703186e-05,
  "fixed_effect_variance_log_frequency:lex_emb_norm": 0.10623352606796103,
  "random_effect_variance_semantic_role": 0.0033499162305793083,
  "random_effect_variance_syntactic_role": 0.03341352531921179,
  "random_effect_variance_valence": 0.010105474375326436,
  "random_effect_variance_dominance": 0.006374582779255562
}