{
  "formula": "log_he_she_odds ~ C(tense) + C(semantic_role) + C(syntactic_role) + C(valence) + C(dominance) + log_frequency + lex_emb_norm + C(tense):C(syntactic_role) + C(tense):log_frequency + C(semantic_role):C(syntactic_role) + C(semantic_role):lex_emb_norm + C(syntactic_role):C(dominance) + C(syntactic_role):log_frequency + C(syntactic_role):lex_emb_norm + C(valence):C(dominance) + C(dominance):lex_emb_norm + profession_embedding_1 + profession_embedding_2 + profession_embedding_3 + profession_embedding_4 + profession_embedding_5",
  "model_type": "OLS",
  "optimizer": "closed_form",
  "converged": true,
  "nobs": 15360,
  "aic": 49720.74346727482,
  "bic": 49980.487215502675,
  "log_likelihood": -24826.37173363741,
  "residual_variance": 1.4872658211920518,
  "R2m": 0.2663294632482739,
  "R2c": 0.2663294632482739,
  "warnings": [],
  "fixed_effect_variance_profession_embedding": 1.4902713483803234,
  "fixed_effect_variance_Intercept": 2.019615402743573e-28,
  "fixed_effect_variance_C(tense)": 0.002829229850219885,
  "fixed_effect_variance_C(semantic_role)": 0.005229750349648146,
  "fixed_effect_variance_C(syntactic_role)": 0.05007417391475706,
  "fixed_effect_variance_C(valence)": 0.002261882434809632,
  "fixed_effect_variance_C(dominance)": 0.01941616021978417,
  "fixed_effect_variance_C(tense):C(syntactic_role)": 0.0013276824153265934,
  "fixed_effect_variance_C(semantic_role):C(syntactic_role)": 0.0022697622637182996,
  "fixed_effect_variance_C(syntactic_role):C(dominance)": 0.0012116207843495545,
  "fixed_effect_variance_C(valence):C(dominance)": 0.000466732228639983,
  "fixed_effect_variance_log_frequency": 0.38232658659205226,
  "fixed_effect_variance_C(tense):log_frequency": 0.009460569697020067,
  "fixed_effect_variance_C(syntactic_role):log_frequency": 0.0033819838182962045,
  "fixed_effect_variance_lex_emb_norm": 0.05088038834734513,
  "fixed_effect_variance_C(semantic_role):lex_emb_norm": 0.00886140257782137,
  "fixed_effect_variance_C(syntactic_role):lex_emb_norm": 0.04366181239433979,
  "fixed_effect_variance_C(dominance):lex_emb_norm": 0.018190112737991898
}