{
  "formula": "log_he_she_odds ~ C(tense) + C(semantic_role) + C(syntactic_role) + C(valence) + C(dominance) + log_frequency + lex_emb_norm + C(tense):C(syntactic_role) + C(tense):C(valence) + C(tense):C(dominance) + C(tense):log_frequency + C(semantic_role):C(syntactic_role) + C(semantic_role):lex_emb_norm + C(syntactic_role):C(valence) + C(syntactic_role):C(dominance) + C(syntactic_role):log_frequency + C(valence):C(dominance) + log_frequency:lex_emb_norm + profession_embedding_1 + profession_embedding_2 + profession_embedding_3 + profession_embedding_4 + profession_embedding_5",
  "model_type": "OLS",
  "optimizer": "closed_form",
  "converged": true,
  "nobs": 15360,
  "aic": 54145.35224002772,
  "bic": 54481.49120832259,
  "log_likelihood": -27028.67612001386,
  "residual_variance": 1.9824837890879246,
  "R2m": 0.28203065069759226,
  "R2c": 0.28203065069759226,
  "warnings": [],
  "fixed_effect_variance_profession_embedding": 1.3813843923242688,
  "fixed_effect_variance_Intercept": 0.0,
  "fixed_effect_variance_C(tense)": 0.018534005142811668,
  "fixed_effect_variance_C(semantic_role)": 0.0004742092282543434,
  "fixed_effect_variance_C(syntactic_role)": 0.12861670475729517,
  "fixed_effect_variance_C(valence)": 0.0012626999486585783,
  "fixed_effect_variance_C(dominance)": 0.002542277616284866,
  "fixed_effect_variance_C(tense):C(syntactic_role)": 0.0033271493946558516,
  "fixed_effect_variance_C(tense):C(valence)": 0.005174492374313301,
  "fixed_effect_variance_C(tense):C(dominance)": 0.007703377280711197,
  "fixed_effect_variance_C(semantic_role):C(syntactic_role)": 0.006239473700491143,
  "fixed_effect_variance_C(syntactic_role):C(valence)": 0.002081420549154386,
  "fixed_effect_variance_C(syntactic_role):C(dominance)": 0.0023882115171913526,
  "fixed_effect_variance_C(valence):C(dominance)": 0.00024275491479297743,
  "fixed_effect_variance_log_frequency": 0.19673830879608778,
  "fixed_effect_variance_C(tense):log_frequency": 0.008639021396400189,
  "fixed_effect_variance_C(syntactic_role):log_frequency": 0.004689917299515373,
  "fixed_effect_variance_lex_emb_norm": 0.6439618166157206,
  "fixed_effect_variance_C(semantic_role):lex_emb_norm": 0.0008779362672795065,
  "fixed_effect_variance_log_frequency:lex_emb_norm": 3.3635417070820206
}