{
  "formula": "log_he_she_odds ~ C(tense) + C(semantic_role) + C(syntactic_role) + C(valence) + C(dominance) + log_frequency + lex_emb_norm + C(tense):C(syntactic_role) + C(tense):C(valence) + C(tense):C(dominance) + C(tense):log_frequency + C(tense):lex_emb_norm + C(semantic_role):C(syntactic_role) + C(semantic_role):C(valence) + C(semantic_role):C(dominance) + C(semantic_role):log_frequency + C(syntactic_role):C(valence) + C(syntactic_role):C(dominance) + C(syntactic_role):lex_emb_norm + C(valence):C(dominance) + C(valence):log_frequency + C(valence):lex_emb_norm + C(dominance):log_frequency + C(dominance):lex_emb_norm + log_frequency:lex_emb_norm + profession_embedding_1 + profession_embedding_2 + profession_embedding_3 + profession_embedding_4 + profession_embedding_5",
  "model_type": "OLS",
  "optimizer": "closed_form",
  "converged": true,
  "nobs": 15360,
  "aic": 48408.019489624094,
  "bic": 48828.19319999268,
  "log_likelihood": -24149.009744812047,
  "residual_variance": 1.3635783709577822,
  "R2m": 0.3215934388951982,
  "R2c": 0.3215934388951982,
  "warnings": [],
  "fixed_effect_variance_profession_embedding": 1.2437984842099596,
  "fixed_effect_variance_Intercept": 5.049038506858933e-29,
  "fixed_effect_variance_C(tense)": 0.009788585143579815,
  "fixed_effect_variance_C(semantic_role)": 0.006998495853122323,
  "fixed_effect_variance_C(syntactic_role)": 0.00024180440577615614,
  "fixed_effect_variance_C(valence)": 2.6084198937592707e-05,
  "fixed_effect_variance_C(dominance)": 1.0818933309190385e-06,
  "fixed_effect_variance_C(tense):C(syntactic_role)": 0.0017563099453621988,
  "fixed_effect_variance_C(tense):C(valence)": 0.0010153322016836477,
  "fixed_effect_variance_C(tense):C(dominance)": 0.001507203394869413,
  "fixed_effect_variance_C(semantic_role):C(syntactic_role)": 0.004486468727580457,
  "fixed_effect_variance_C(semantic_role):C(valence)": 0.0004884154985887285,
  "fixed_effect_variance_C(semantic_role):C(dominance)": 0.0006000859494872445,
  "fixed_effect_variance_C(syntactic_role):C(valence)": 1.5109031380601783e-05,
  "fixed_effect_variance_C(syntactic_role):C(dominance)": 6.875925832622754e-05,
  "fixed_effect_variance_C(valence):C(dominance)": 0.00045023041042009334,
  "fixed_effect_variance_log_frequency": 3.017595320779406,
  "fixed_effect_variance_C(tense):log_frequency": 0.023966461051123687,
  "fixed_effect_variance_C(semantic_role):log_frequency": 0.0009395286460406636,
  "fixed_effect_variance_C(valence):log_frequency": 0.005837717967535716,
  "fixed_effect_variance_C(dominance):log_frequency": 0.0012346628893254868,
  "fixed_effect_variance_lex_emb_norm": 2.4743031410437886,
  "fixed_effect_variance_C(tense):lex_emb_norm": 0.011862026546582114,
  "fixed_effect_variance_C(syntactic_role):lex_emb_norm": 0.0013361017781479932,
  "fixed_effect_variance_C(valence):lex_emb_norm": 0.011365745317124743,
  "fixed_effect_variance_C(dominance):lex_emb_norm": 0.0009226057701245921,
  "fixed_effect_variance_log_frequency:lex_emb_norm": 5.224508167337336
}