{
  "formula": "log_he_she_odds ~ C(tense) + C(semantic_role) + C(syntactic_role) + C(valence) + C(dominance) + log_frequency + lex_emb_norm + C(tense):C(semantic_role) + C(tense):C(syntactic_role) + C(tense):C(valence) + C(tense):C(dominance) + C(tense):log_frequency + C(tense):lex_emb_norm + C(semantic_role):C(syntactic_role) + C(semantic_role):C(valence) + C(semantic_role):C(dominance) + C(semantic_role):log_frequency + C(semantic_role):lex_emb_norm + C(syntactic_role):C(valence) + C(syntactic_role):C(dominance) + C(syntactic_role):lex_emb_norm + C(valence):C(dominance) + C(valence):log_frequency + C(valence):lex_emb_norm + C(dominance):log_frequency + C(dominance):lex_emb_norm + profession_embedding_1 + profession_embedding_2 + profession_embedding_3 + profession_embedding_4 + profession_embedding_5",
  "model_type": "OLS",
  "optimizer": "closed_form",
  "converged": true,
  "nobs": 15360,
  "aic": 48851.90099787142,
  "bic": 49310.27231827351,
  "log_likelihood": -24365.95049893571,
  "residual_variance": 1.4031035962100986,
  "R2m": 0.30215692965611496,
  "R2c": 0.30215692965611496,
  "warnings": [],
  "fixed_effect_variance_profession_embedding": 1.168387784506603,
  "fixed_effect_variance_Intercept": 5.049038506858933e-29,
  "fixed_effect_variance_C(tense)": 0.010402123106075106,
  "fixed_effect_variance_C(semantic_role)": 0.004591589659506993,
  "fixed_effect_variance_C(syntactic_role)": 0.0002418044057762721,
  "fixed_effect_variance_C(valence)": 2.6084198937751654e-05,
  "fixed_effect_variance_C(dominance)": 1.0818933309324206e-06,
  "fixed_effect_variance_C(tense):C(semantic_role)": 0.0002771067995595771,
  "fixed_effect_variance_C(tense):C(syntactic_role)": 0.001756309945362353,
  "fixed_effect_variance_C(tense):C(valence)": 0.0010153322016835517,
  "fixed_effect_variance_C(tense):C(dominance)": 0.001507203394869331,
  "fixed_effect_variance_C(semantic_role):C(syntactic_role)": 0.004486468727581037,
  "fixed_effect_variance_C(semantic_role):C(valence)": 0.0004884154985885586,
  "fixed_effect_variance_C(semantic_role):C(dominance)": 0.0006000859494873755,
  "fixed_effect_variance_C(syntactic_role):C(valence)": 1.5109031380613042e-05,
  "fixed_effect_variance_C(syntactic_role):C(dominance)": 6.87592583262709e-05,
  "fixed_effect_variance_C(valence):C(dominance)": 0.00045023041042026465,
  "fixed_effect_variance_log_frequency": 0.3003758597297557,
  "fixed_effect_variance_C(tense):log_frequency": 0.02396646105111973,
  "fixed_effect_variance_C(semantic_role):log_frequency": 0.0021321923666414383,
  "fixed_effect_variance_C(valence):log_frequency": 0.005837717967536027,
  "fixed_effect_variance_C(dominance):log_frequency": 0.0012346628893236072,
  "fixed_effect_variance_lex_emb_norm": 0.05385596095351647,
  "fixed_effect_variance_C(tense):lex_emb_norm": 0.011862026546582033,
  "fixed_effect_variance_C(semantic_role):lex_emb_norm": 0.0006532434552200395,
  "fixed_effect_variance_C(syntactic_role):lex_emb_norm": 0.0013361017781480214,
  "fixed_effect_variance_C(valence):lex_emb_norm": 0.011365745317125161,
  "fixed_effect_variance_C(dominance):lex_emb_norm": 0.0009226057701246099
}