{
  "formula": "log_he_she_odds ~ C(tense) + C(syntactic_role) + C(valence) + C(dominance) + C(semantic_role) + C(tense):C(syntactic_role) + C(tense):C(valence) + C(tense):C(semantic_role) + C(syntactic_role):C(valence) + C(syntactic_role):C(dominance) + C(syntactic_role):C(semantic_role)",
  "re_formula": "1 + C(semantic_role) + C(syntactic_role)",
  "group_col": "profession",
  "optimizer": "lbfgs",
  "converged": true,
  "aic": 5599.141651877631,
  "bic": 5837.591172050733,
  "log_likelihood": -2764.5708259388157,
  "nobs": 6720,
  "residual_variance": 0.13005355993318457,
  "R2m": 0.030791906313238655,
  "R2c": 0.9183036157464932
}