{
  "formula": "log_he_she_odds ~ C(tense) + C(semantic_role) + C(syntactic_role) + C(valence) + C(dominance) + log_frequency + lex_emb_norm + C(tense):C(semantic_role) + C(tense):C(syntactic_role) + C(tense):C(valence) + C(tense):C(dominance) + C(tense):log_frequency + C(semantic_role):C(syntactic_role) + C(semantic_role):C(valence) + C(semantic_role):log_frequency + C(semantic_role):lex_emb_norm + C(syntactic_role):C(valence) + C(syntactic_role):C(dominance) + C(syntactic_role):log_frequency + C(syntactic_role):lex_emb_norm + C(valence):log_frequency + C(valence):lex_emb_norm + C(dominance):log_frequency + log_frequency:lex_emb_norm + profession_embedding_1 + profession_embedding_2 + profession_embedding_3 + profession_embedding_4 + profession_embedding_5",
  "model_type": "OLS",
  "optimizer": "closed_form",
  "converged": true,
  "nobs": 15360,
  "aic": 52731.16541080226,
  "bic": 53143.69959916415,
  "log_likelihood": -26311.58270540113,
  "residual_variance": 1.8069350806160458,
  "R2m": 0.24972348306973458,
  "R2c": 0.24972348306973458,
  "warnings": [],
  "fixed_effect_variance_profession_embedding": 1.059231545994675,
  "fixed_effect_variance_Intercept": 5.049038506858933e-29,
  "fixed_effect_variance_C(tense)": 0.004941580779499116,
  "fixed_effect_variance_C(semantic_role)": 0.013088702497562677,
  "fixed_effect_variance_C(syntactic_role)": 0.014412071722822948,
  "fixed_effect_variance_C(valence)": 0.008388500154862047,
  "fixed_effect_variance_C(dominance)": 6.723146258543088e-05,
  "fixed_effect_variance_C(tense):C(semantic_role)": 0.002682390455910511,
  "fixed_effect_variance_C(tense):C(syntactic_role)": 0.003166729378441557,
  "fixed_effect_variance_C(tense):C(valence)": 0.0013111969943543974,
  "fixed_effect_variance_C(tense):C(dominance)": 0.0017316542799524152,
  "fixed_effect_variance_C(semantic_role):C(syntactic_role)": 0.008519498917511031,
  "fixed_effect_variance_C(semantic_role):C(valence)": 2.8951998985869387e-05,
  "fixed_effect_variance_C(syntactic_role):C(valence)": 0.0028316961586345303,
  "fixed_effect_variance_C(syntactic_role):C(dominance)": 0.0005443245804710392,
  "fixed_effect_variance_log_frequency": 0.7853648622240395,
  "fixed_effect_variance_C(tense):log_frequency": 0.007979343513910572,
  "fixed_effect_variance_C(semantic_role):log_frequency": 0.0023697426549421597,
  "fixed_effect_variance_C(syntactic_role):log_frequency": 0.01174602344996204,
  "fixed_effect_variance_C(valence):log_frequency": 0.00037834309976190545,
  "fixed_effect_variance_C(dominance):log_frequency": 0.00014502545167348324,
  "fixed_effect_variance_lex_emb_norm": 3.1283146078263964,
  "fixed_effect_variance_C(semantic_role):lex_emb_norm": 0.0009441309656653522,
  "fixed_effect_variance_C(syntactic_role):lex_emb_norm": 0.002692122613206842,
  "fixed_effect_variance_C(valence):lex_emb_norm": 0.00030537515617368296,
  "fixed_effect_variance_log_frequency:lex_emb_norm": 8.991549552261587
}