{
  "formula": "log_he_she_odds ~ C(tense) + C(semantic_role) + C(syntactic_role) + C(valence) + C(dominance) + log_frequency + lex_emb_norm + C(tense):C(semantic_role) + C(tense):C(syntactic_role) + C(tense):C(valence) + C(tense):C(dominance) + C(tense):log_frequency + C(semantic_role):C(syntactic_role) + C(semantic_role):log_frequency + C(semantic_role):lex_emb_norm + C(syntactic_role):C(valence) + C(syntactic_role):log_frequency + C(syntactic_role):lex_emb_norm + C(valence):C(dominance) + C(valence):log_frequency + log_frequency:lex_emb_norm + profession_embedding_1 + profession_embedding_2 + profession_embedding_3 + profession_embedding_4 + profession_embedding_5",
  "model_type": "OLS",
  "optimizer": "closed_form",
  "converged": true,
  "nobs": 15360,
  "aic": 52726.825764285306,
  "bic": 53116.44138662709,
  "log_likelihood": -26312.412882142653,
  "residual_variance": 1.806776282516562,
  "R2m": 0.24964237684841817,
  "R2c": 0.24964237684841817,
  "warnings": [],
  "fixed_effect_variance_profession_embedding": 1.0592315459946693,
  "fixed_effect_variance_Intercept": 0.0,
  "fixed_effect_variance_C(tense)": 0.004941580779499306,
  "fixed_effect_variance_C(semantic_role)": 0.013809168753132706,
  "fixed_effect_variance_C(syntactic_role)": 0.011359352896118488,
  "fixed_effect_variance_C(valence)": 0.008424033300048667,
  "fixed_effect_variance_C(dominance)": 0.00012331874959487145,
  "fixed_effect_variance_C(tense):C(semantic_role)": 0.002682390455910089,
  "fixed_effect_variance_C(tense):C(syntactic_role)": 0.0031667293784415807,
  "fixed_effect_variance_C(tense):C(valence)": 0.001311196994354552,
  "fixed_effect_variance_C(tense):C(dominance)": 0.001731654279952361,
  "fixed_effect_variance_C(semantic_role):C(syntactic_role)": 0.008519498917510745,
  "fixed_effect_variance_C(syntactic_role):C(valence)": 0.002831696158634568,
  "fixed_effect_variance_C(valence):C(dominance)": 8.682996016253945e-05,
  "fixed_effect_variance_log_frequency": 0.7749830452789863,
  "fixed_effect_variance_C(tense):log_frequency": 0.007979343513911646,
  "fixed_effect_variance_C(semantic_role):log_frequency": 0.002369742654941684,
  "fixed_effect_variance_C(syntactic_role):log_frequency": 0.011746023449964763,
  "fixed_effect_variance_C(valence):log_frequency": 0.00012355311543497328,
  "fixed_effect_variance_lex_emb_norm": 3.1464567325406567,
  "fixed_effect_variance_C(semantic_role):lex_emb_norm": 0.0009441309656675013,
  "fixed_effect_variance_C(syntactic_role):lex_emb_norm": 0.0026921226132064235,
  "fixed_effect_variance_log_frequency:lex_emb_norm": 8.991549552261468
}