{
  "formula": "log_he_she_odds ~ C(tense) + C(semantic_role) + C(syntactic_role) + C(valence) + C(dominance) + log_frequency + lex_emb_norm + C(tense):C(semantic_role) + C(tense):C(syntactic_role) + C(tense):C(valence) + C(tense):C(dominance) + C(semantic_role):C(syntactic_role) + C(semantic_role):C(valence) + C(semantic_role):C(dominance) + C(semantic_role):log_frequency + C(semantic_role):lex_emb_norm + C(syntactic_role):C(valence) + C(syntactic_role):C(dominance) + C(syntactic_role):log_frequency + C(syntactic_role):lex_emb_norm + C(valence):C(dominance) + C(valence):lex_emb_norm + log_frequency:lex_emb_norm + profession_embedding_1 + profession_embedding_2 + profession_embedding_3 + profession_embedding_4 + profession_embedding_5",
  "model_type": "OLS",
  "optimizer": "closed_form",
  "converged": true,
  "nobs": 15360,
  "aic": 54156.5576270432,
  "bic": 54530.89420537158,
  "log_likelihood": -27029.2788135216,
  "residual_variance": 1.9832868279019384,
  "R2m": 0.28197430532716883,
  "R2c": 0.28197430532716883,
  "warnings": [],
  "fixed_effect_variance_profession_embedding": 1.3813843923242695,
  "fixed_effect_variance_Intercept": 2.019615402743573e-28,
  "fixed_effect_variance_C(tense)": 0.05099758536278822,
  "fixed_effect_variance_C(semantic_role)": 0.0027900231842103184,
  "fixed_effect_variance_C(syntactic_role)": 0.12094941371085517,
  "fixed_effect_variance_C(valence)": 0.0012551582112750224,
  "fixed_effect_variance_C(dominance)": 0.001902783758205578,
  "fixed_effect_variance_C(tense):C(semantic_role)": 0.00054364894413422,
  "fixed_effect_variance_C(tense):C(syntactic_role)": 0.0033271493946555493,
  "fixed_effect_variance_C(tense):C(valence)": 0.005174492374310252,
  "fixed_effect_variance_C(tense):C(dominance)": 0.007703377280711478,
  "fixed_effect_variance_C(semantic_role):C(syntactic_role)": 0.006239473700491785,
  "fixed_effect_variance_C(semantic_role):C(valence)": 0.0006217927693438924,
  "fixed_effect_variance_C(semantic_role):C(dominance)": 0.0001387238383723381,
  "fixed_effect_variance_C(syntactic_role):C(valence)": 0.0020814205491539975,
  "fixed_effect_variance_C(syntactic_role):C(dominance)": 0.0023882115171908313,
  "fixed_effect_variance_C(valence):C(dominance)": 0.00024275491479317635,
  "fixed_effect_variance_log_frequency": 0.18167758669436637,
  "fixed_effect_variance_C(semantic_role):log_frequency": 0.00101644920629694,
  "fixed_effect_variance_C(syntactic_role):log_frequency": 0.006185468248000528,
  "fixed_effect_variance_lex_emb_norm": 0.6498033959112105,
  "fixed_effect_variance_C(semantic_role):lex_emb_norm": 0.0025415329478593747,
  "fixed_effect_variance_C(syntactic_role):lex_emb_norm": 0.0004611067329885197,
  "fixed_effect_variance_C(valence):lex_emb_norm": 0.00023923131674434523,
  "fixed_effect_variance_log_frequency:lex_emb_norm": 3.3635417070818945
}