{
  "formula": "log_he_she_odds ~ C(tense) + C(semantic_role) + C(syntactic_role) + C(valence) + C(dominance) + log_frequency + lex_emb_norm + C(tense):C(semantic_role) + C(tense):C(syntactic_role) + C(tense):C(valence) + C(tense):C(dominance) + C(tense):log_frequency + C(tense):lex_emb_norm + C(semantic_role):C(syntactic_role) + C(semantic_role):C(valence) + C(semantic_role):C(dominance) + C(semantic_role):log_frequency + C(semantic_role):lex_emb_norm + C(syntactic_role):C(valence) + C(syntactic_role):C(dominance) + C(syntactic_role):log_frequency + C(syntactic_role):lex_emb_norm + C(valence):C(dominance) + C(valence):log_frequency + C(dominance):log_frequency + C(dominance):lex_emb_norm + log_frequency:lex_emb_norm",
  "re_formula": "1 + C(semantic_role) + C(syntactic_role) + C(valence) + C(dominance)",
  "group_col": "profession",
  "optimizer": "lbfgs",
  "converged": false,
  "warning_count": 4,
  "warnings": [
    "ConvergenceWarning: Maximum Likelihood optimization failed to converge. Check mle_retvals",
    "ConvergenceWarning: MixedLM optimization failed, trying a different optimizer may help.",
    "ConvergenceWarning: Gradient optimization failed, |grad| = 64.038890",
    "ConvergenceWarning: The Hessian matrix at the estimated parameter values is not positive definite."
  ],
  "numerical_issue_warnings": true,
  "aic": 10283.941513580125,
  "bic": 10833.987098062644,
  "log_likelihood": -5069.970756790062,
  "nobs": 15360,
  "residual_variance": 0.10719650391794874,
  "R2m": 0.04352113340925794,
  "R2c": 0.9621479546733901,
  "fixed_effect_variance_Intercept": 3.155649066786833e-30,
  "fixed_effect_variance_C(tense)": 0.04080695567273601,
  "fixed_effect_variance_C(semantic_role)": 0.002229969988975463,
  "fixed_effect_variance_C(syntactic_role)": 0.03974230589901101,
  "fixed_effect_variance_C(valence)": 0.0035467048463939527,
  "fixed_effect_variance_C(dominance)": 0.026889947197680047,
  "fixed_effect_variance_C(tense):C(semantic_role)": 0.0016022053176247743,
  "fixed_effect_variance_C(tense):C(syntactic_role)": 0.0013276824153261144,
  "fixed_effect_variance_C(tense):C(valence)": 0.0008946256730957194,
  "fixed_effect_variance_C(tense):C(dominance)": 0.0005883946827885172,
  "fixed_effect_variance_C(semantic_role):C(syntactic_role)": 0.0022697622637177918,
  "fixed_effect_variance_C(semantic_role):C(valence)": 0.0002646340865301355,
  "fixed_effect_variance_C(semantic_role):C(dominance)": 0.0002799994392207052,
  "fixed_effect_variance_C(syntactic_role):C(valence)": 0.00019811184694697658,
  "fixed_effect_variance_C(syntactic_role):C(dominance)": 0.0012116207843495663,
  "fixed_effect_variance_C(valence):C(dominance)": 0.00046673222864016613,
  "fixed_effect_variance_log_frequency": 14.883805149422196,
  "fixed_effect_variance_C(tense):log_frequency": 0.02995480449489492,
  "fixed_effect_variance_C(semantic_role):log_frequency": 0.00018376137526343006,
  "fixed_effect_variance_C(syntactic_role):log_frequency": 0.002359005939864727,
  "fixed_effect_variance_C(valence):log_frequency": 0.00032773634356390017,
  "fixed_effect_variance_C(dominance):log_frequency": 0.0027037324708670436,
  "fixed_effect_variance_lex_emb_norm": 1.8001616505453648,
  "fixed_effect_variance_C(tense):lex_emb_norm": 0.06758566711455082,
  "fixed_effect_variance_C(semantic_role):lex_emb_norm": 0.012643625639963775,
  "fixed_effect_variance_C(syntactic_role):lex_emb_norm": 0.03363199551807621,
  "fixed_effect_variance_C(dominance):lex_emb_norm": 0.0474559563123472,
  "fixed_effect_variance_log_frequency:lex_emb_norm": 23.082812694948036,
  "random_effect_variance_semantic_role": 0.0944401118938297,
  "random_effect_variance_syntactic_role": 0.06867477245588352,
  "random_effect_variance_valence": 0.09043835189937398,
  "random_effect_variance_dominance": 0.08319588706493684
}