{
  "formula": "log_he_she_odds ~ C(tense) + C(semantic_role) + C(syntactic_role) + C(valence) + C(dominance) + log_frequency + lex_emb_norm + C(tense):C(syntactic_role) + C(tense):C(valence) + C(tense):C(dominance) + C(tense):log_frequency + C(semantic_role):C(syntactic_role) + C(semantic_role):C(valence) + C(syntactic_role):C(valence) + C(syntactic_role):C(dominance) + C(valence):C(dominance) + log_frequency:lex_emb_norm + profession_embedding_1 + profession_embedding_2 + profession_embedding_3 + profession_embedding_4 + profession_embedding_5",
  "model_type": "OLS",
  "optimizer": "closed_form",
  "converged": true,
  "nobs": 15360,
  "aic": 54145.184335240345,
  "bic": 54473.68378152852,
  "log_likelihood": -27029.592167620172,
  "residual_variance": 1.9825908222419781,
  "R2m": 0.28194500833700753,
  "R2c": 0.28194500833700753,
  "warnings": [],
  "fixed_effect_variance_profession_embedding": 1.3813843923242737,
  "fixed_effect_variance_Intercept": 5.049038506858933e-29,
  "fixed_effect_variance_C(tense)": 0.01853400514281139,
  "fixed_effect_variance_C(semantic_role)": 0.004090370718078886,
  "fixed_effect_variance_C(syntactic_role)": 0.08767718870166583,
  "fixed_effect_variance_C(valence)": 0.0024931212135386677,
  "fixed_effect_variance_C(dominance)": 0.002542277616283746,
  "fixed_effect_variance_C(tense):C(syntactic_role)": 0.003327149394655632,
  "fixed_effect_variance_C(tense):C(valence)": 0.005174492374312593,
  "fixed_effect_variance_C(tense):C(dominance)": 0.007703377280711834,
  "fixed_effect_variance_C(semantic_role):C(syntactic_role)": 0.0062394737004910356,
  "fixed_effect_variance_C(semantic_role):C(valence)": 0.0006217927693443303,
  "fixed_effect_variance_C(syntactic_role):C(valence)": 0.0020814205491543887,
  "fixed_effect_variance_C(syntactic_role):C(dominance)": 0.002388211517191182,
  "fixed_effect_variance_C(valence):C(dominance)": 0.00024275491479289993,
  "fixed_effect_variance_log_frequency": 0.17960812216468494,
  "fixed_effect_variance_C(tense):log_frequency": 0.008639021396398975,
  "fixed_effect_variance_lex_emb_norm": 0.6323283500907705,
  "fixed_effect_variance_log_frequency:lex_emb_norm": 3.3635417070817257
}